llm_patch_driver/__init__.py
llm_patch_driver/py.typed
llm_patch_driver/driver/__init__.py
llm_patch_driver/driver/driver.py
llm_patch_driver/driver/prompts.py
llm_patch_driver/llm/__init__.py
llm_patch_driver/llm/base_adapter.py
llm_patch_driver/llm/base_tool.py
llm_patch_driver/llm/google_adapters.py
llm_patch_driver/llm/litellm_adapters.py
llm_patch_driver/llm/openai_adapters.py
llm_patch_driver/llm/schemas.py
llm_patch_driver/patch/__init__.py
llm_patch_driver/patch/base_patch.py
llm_patch_driver/patch/json/json_patch.py
llm_patch_driver/patch/json/prompts.py
llm_patch_driver/patch/string/prompts.py
llm_patch_driver/patch/string/string_patch.py
llm_patch_driver/patch_target/__init__.py
llm_patch_driver/patch_target/prompts.py
llm_patch_driver/patch_target/target.py
llm_patch_driver-0.1.3.dist-info/METADATA
llm_patch_driver-0.1.3.dist-info/WHEEL
llm_patch_driver-0.1.3.dist-info/licenses/LICENSE
llm_patch_driver-0.1.3.dist-info/RECORD
