Metadata-Version: 2.4
Name: llm-patch-driver
Version: 0.1.3
Summary: LLM Patch Driver is a framework for patching data objects using LLMs. It can generate and apply a single patch, or start the patching loop to fix complex validation issues.
Project-URL: Homepage, https://github.com/NickSherrow/llm_patch_driver
Project-URL: Repository, https://github.com/NickSherrow/llm_patch_driver
Project-URL: Issues, https://github.com/NickSherrow/llm_patch_driver
Author-email: Nikita Shirobokov <shirobokov@me.com>
License: MIT License
License-File: LICENSE
Classifier: License :: OSI Approved :: MIT License
Requires-Python: >=3.12
Requires-Dist: glom>=24.11.0
Requires-Dist: jsonpatch>=1.33
Requires-Dist: pydantic>=2.11.7
Requires-Dist: sortedcontainers>=2.4.0
Requires-Dist: spacy>=3.8.7
